{"convertConfig":{"advancedArgs":"","aippBtnSelection":[{"aippButtonName":"images","aippCropBtnSelected":false,"aippMeanBtnSelected":true,"aippMinBtnSelected":false,"aippMultiplierBtnSelected":false,"aippOpenBtSelected":true,"aippPaddingBtnSelected":false,"aippPreImgBtnSelected":true,"aippResizeBtnSelected":false}],"aippData":[{"aippMode":"STATIC","bottomPaddingSize":"","crop":false,"cropH":"","cropStartX":"","cropStartY":"","cropW":"","enable":true,"inputImageFormat":"BGR_PLANAR","inputImageFormatShowValue":"BGR planar","inputImageSizeH":"640","inputImageSizeW":"640","inputIndex":"0","leftPaddingSize":"","maxImageSize":"","meanLess0":"0","meanLess1":"0","meanLess2":"0","meanLess3":"","minChn0":"","minChn1":"","minChn2":"","minChn3":"","modelImageFormat":"RGB","modelImageFormatEnable":true,"modelImageType":"BT_601NARROW","multiFactor0":"1","multiFactor1":"1","multiFactor2":"1","multiFactor3":"","padding":false,"resize":false,"resizeOutputH":"","resizeOutputW":"","rightPaddingSize":"","topPaddingSize":""}],"aippMode":"static","aippSelection":true,"autoTuneBtnSeleted":false,"autoTuneMode":"","batchList":[],"batchNum":"1","calData":[],"closeFusionRule":"false","compileMode":"0","customOpsPath":"","dumpData":"0","dynamicBatch":false,"dynamicBatchContent":"","dynamicImgSize":false,"dynamicImgSizeContent":"","encryptBtnSelection":true,"history":true,"historyItemName":"yolox_config","inputFormat":"NCHW","inputFormatChooseEnable":true,"inputShape":[{"name":"images","number":"1","channel":"3","width":"640","height":"640","inputShape":"1,3,640,640","inputIndex":"0","inputType":"UINT8","addByUser":false,"imagesFile":"./data/image_ref_list.txt"}],"inputType":"FP32","inputTypeChanged":false,"logLevel":"0","markedNodes":[],"modelDataType":"FLOATING","modelFilePath":"./onnx_model/yolox_s.onnx","modelName":"yolox","modelType":"ONNX","needAdvancedArgs":false,"needSaveOriginalModel":"true","onlineModelType":"0","outNodes":[],"outNodesItem":[],"outputFolderPath":"~/modelzoo/yolox","outputSoc":"","outputType":"FP32","outputTypeSwitch":false,"path2SaveOm":"./model","pluginPath":"","quantParamFilePath":"","shouldCopyOm":true,"targetType":"DEVICE","weightFilePath":""},"name":"yolox_config"}